osc_docker_builder/__init__.py
osc_docker_builder/osc.py
osc_docker_builder/templates/Dockerfile.j2
osc_docker_builder/templates/requirements.j2
osc_docker_builder-2.3.dist-info/DESCRIPTION.rst
osc_docker_builder-2.3.dist-info/METADATA
osc_docker_builder-2.3.dist-info/RECORD
osc_docker_builder-2.3.dist-info/WHEEL
osc_docker_builder-2.3.dist-info/entry_points.txt
osc_docker_builder-2.3.dist-info/metadata.json
osc_docker_builder-2.3.dist-info/top_level.txt
