Metadata-Version: 2.0
Name: osc-docker-builder
Version: 2.3
Summary: Docker image builder for Openstack python clients
Home-page: http://github.com/engapa/osc-docker-builder.git
Author: Enrique Garcia Pablos
Author-email: engapa@gmail.com
License: Apache 2.0
Platform: UNKNOWN
Classifier: Programming Language :: Python
Classifier: Programming Language :: Python :: 2.7
Classifier: Programming Language :: Python :: 3.4
Classifier: Programming Language :: Python :: Implementation :: CPython
Classifier: Programming Language :: Python :: Implementation :: PyPy
Classifier: Operating System :: OS Independent
